dbt_adapter_tests/__init__.py
pytest_dbt_adapter/__init__.py
pytest_dbt_adapter/builtin.py
pytest_dbt_adapter/exceptions.py
pytest_dbt_adapter/spec_file.py
pytest_dbt_adapter/projects/base.yml
pytest_dbt_adapter/projects/data_test_ephemerals.yml
pytest_dbt_adapter/projects/data_tests.yml
pytest_dbt_adapter/projects/empty.yml
pytest_dbt_adapter/projects/ephemeral.yml
pytest_dbt_adapter/projects/incremental.yml
pytest_dbt_adapter/projects/schema_tests.yml
pytest_dbt_adapter/projects/snapshot_cc.yml
pytest_dbt_adapter/projects/snapshot_ts.yml
pytest_dbt_adapter/sequences/base.yml
pytest_dbt_adapter/sequences/data_test.yml
pytest_dbt_adapter/sequences/data_test_ephemeral_models.yml
pytest_dbt_adapter/sequences/empty.yml
pytest_dbt_adapter/sequences/ephemeral.yml
pytest_dbt_adapter/sequences/incremental.yml
pytest_dbt_adapter/sequences/schema_test.yml
pytest_dbt_adapter/sequences/snapshot_strategy_check_cols.yml
pytest_dbt_adapter/sequences/snapshot_strategy_timestamp.yml
pytest_dbt_adapter-0.6.0.dist-info/METADATA
pytest_dbt_adapter-0.6.0.dist-info/WHEEL
pytest_dbt_adapter-0.6.0.dist-info/entry_points.txt
pytest_dbt_adapter-0.6.0.dist-info/top_level.txt
pytest_dbt_adapter-0.6.0.dist-info/RECORD
