Metadata-Version: 2.1
Name: pytest-dbt-adapter
Version: 0.6.0
Summary: A pytest plugin for testing dbt adapter plugins
Home-page: https://github.com/dbt-labs/dbt-adapter-tests
Author: dbt Labs
Author-email: info@dbtlabs.com
License: UNKNOWN
Platform: UNKNOWN
Requires-Python: >=3.6.2
Requires-Dist: py (>=1.3.0)
Requires-Dist: pytest (<7,>=6)
Requires-Dist: pyyaml (>=3.11)
